<?xml version="1.0" encoding="UTF-8"?>
<!DOCTYPE server>

<!--
   automatically generated by xdoclet. do not edit
-->
<server>
   <mbean code="net.sf.hibernate.jmx.HibernateService" name="jboss.jca:service=HibernateFactory">
       <depends>jboss.jca:service=RARDeployer</depends>
       <attribute name="MapResources">org\arbfile\test\dbdemo\User.hbm.xml</attribute>
       <attribute name="JndiName">java:/hibernate/HibernateFactory</attribute>
       <attribute name="Datasource">java:comp/env/espeed</attribute>
       <attribute name="Dialect">net.sf.hibernate.sql.OracleDialect</attribute>
	   <attribute name="UseOuterJoin">false</attribute>
	   <attribute name="ShowSql">false</attribute>
	   <attribute name="TransactionStrategy"></attribute>
   </mbean>
</server>
